Metadata-Version: 2.1
Name: video-maker-ferramentas
Version: 1.0
Summary: Este pacote irá fornecer ferramentas de processamento de vídeo
Author: Luis
Author-email: luis@gmail.com
Keywords: camera,video,processamento
License-File: license.txt
